{
  "project_info": {
    "project_number": "150541578176",
    "firebase_url": "https://mobilett-8e1d5.firebaseio.com",
    "project_id": "mobilett-8e1d5",
    "storage_bucket": "mobilett-8e1d5.appspot.com"
  },
  "client": [
    {
      "client_info": {
        "mobilesdk_app_id": "1:150541578176:android:73f108e4cca6aee8",
        "android_client_info": {
          "package_name": "org.mobilett.version1"
        }
      },
      "oauth_client": [
        {
          "client_id": "150541578176-o7hl6tcsb586b1aqhane1nti3oi099s5.apps.googleusercontent.com",
          "client_type": 1,
          "android_info": {
            "package_name": "org.mobilett.version1",
            "certificate_hash": "6a125d125d7997679810b09a6493b25841238bd5"
          }
        },
        {
          "client_id": "150541578176-51ulblt1fsijtpgdntti8mf0hk4tb1cr.apps.googleusercontent.com",
          "client_type": 3
        }
      ],
      "api_key": [
        {
          "current_key": "AIzaSyDejNIzqOK9D5Ozvg7Hl6_Fipgl3GuzuOw"
        }
      ],
      "services": {
        "analytics_service": {
          "status": 1
        },
        "appinvite_service": {
          "status": 2,
          "other_platform_oauth_client": [
            {
              "client_id": "150541578176-51ulblt1fsijtpgdntti8mf0hk4tb1cr.apps.googleusercontent.com",
              "client_type": 3
            }
          ]
        },
        "ads_service": {
          "status": 2
        }
      }
    }
  ],
  "configuration_version": "1"
}